enum_tools/__init__.py
enum_tools/autoenum.py
enum_tools/custom_enums.py
enum_tools/demo.py
enum_tools/documentation.py
enum_tools/py.typed
enum_tools/utils.py
enum_tools-0.11.0.dist-info/LICENSE
enum_tools-0.11.0.dist-info/METADATA
enum_tools-0.11.0.dist-info/WHEEL
enum_tools-0.11.0.dist-info/entry_points.txt
enum_tools-0.11.0.dist-info/RECORD
