Metadata-Version: 2.1
Name: enum-tools
Version: 0.11.0
Summary: Tools to expand Python's enum module.
Author-email: Dominic Davis-Foster <dominic@davis-foster.co.uk>
License: LGPL-3.0-or-later
Keywords: documentation,enum,sphinx,sphinx-extension
Home-page: https://github.com/domdfcoding/enum_tools
Project-URL: Issue Tracker, https://github.com/domdfcoding/enum_tools/issues
Project-URL: Source Code, https://github.com/domdfcoding/enum_tools
Project-URL: Documentation, https://enum-tools.readthedocs.io/en/latest
Platform: Windows
Platform: macOS
Platform: Linux
Classifier: Development Status :: 4 - Beta
Classifier: Framework :: Sphinx :: Extension
Classifier: Intended Audience :: Developers
Classifier: License :: OSI Approved :: GNU Lesser General Public License v3 or later (LGPLv3+)
Classifier: Operating System :: OS Independent
Classifier: Programming Language :: Python
Classifier: Programming Language :: Python :: 3 :: Only
Classifier: Programming Language :: Python :: 3.6
Classifier: Programming Language :: Python :: 3.7
Classifier: Programming Language :: Python :: 3.8
Classifier: Programming Language :: Python :: 3.9
Classifier: Programming Language :: Python :: 3.10
Classifier: Programming Language :: Python :: 3.11
Classifier: Programming Language :: Python :: Implementation :: CPython
Classifier: Programming Language :: Python :: Implementation :: PyPy
Classifier: Topic :: Documentation
Classifier: Topic :: Documentation :: Sphinx
Classifier: Topic :: Software Development :: Documentation
Classifier: Topic :: Software Development :: Libraries :: Python Modules
Classifier: Topic :: Utilities
Classifier: Typing :: Typed
Requires-Python: >=3.6
Requires-Dist: pygments>=2.6.1
Requires-Dist: typing-extensions>=3.7.4.3
Requires-Dist: sphinx>=3.4.0; extra == 'sphinx'
Requires-Dist: sphinx-jinja2-compat>=0.1.1; extra == 'sphinx'
Requires-Dist: sphinx-toolbox>=2.16.0; extra == 'sphinx'
Requires-Dist: sphinx>=3.4.0; extra == 'all'
Requires-Dist: sphinx-jinja2-compat>=0.1.1; extra == 'all'
Requires-Dist: sphinx-toolbox>=2.16.0; extra == 'all'
Provides-Extra: sphinx
Provides-Extra: all
